{
  "top_50_concepts": [
    {
      "concept": "Political science",
      "count": 288
    },
    {
      "concept": "Law",
      "count": 279
    },
    {
      "concept": "Politics",
      "count": 269
    },
    {
      "concept": "Sociology",
      "count": 228
    },
    {
      "concept": "Political economy",
      "count": 188
    },
    {
      "concept": "Populism",
      "count": 187
    },
    {
      "concept": "Economics",
      "count": 123
    },
    {
      "concept": "Philosophy",
      "count": 106
    },
    {
      "concept": "Democracy",
      "count": 82
    },
    {
      "concept": "Computer science",
      "count": 75
    },
    {
      "concept": "Epistemology",
      "count": 58
    },
    {
      "concept": "Psychology",
      "count": 54
    },
    {
      "concept": "Ideology",
      "count": 47
    },
    {
      "concept": "History",
      "count": 46
    },
    {
      "concept": "Social psychology",
      "count": 37
    },
    {
      "concept": "Linguistics",
      "count": 37
    },
    {
      "concept": "Media studies",
      "count": 36
    },
    {
      "concept": "Archaeology",
      "count": 33
    },
    {
      "concept": "Development economics",
      "count": 32
    },
    {
      "concept": "Social science",
      "count": 30
    },
    {
      "concept": "Physics",
      "count": 27
    },
    {
      "concept": "Chemistry",
      "count": 27
    },
    {
      "concept": "Positive economics",
      "count": 26
    },
    {
      "concept": "Mainstream",
      "count": 24
    },
    {
      "concept": "Mathematics",
      "count": 24
    },
    {
      "concept": "Biochemistry",
      "count": 23
    },
    {
      "concept": "Right wing",
      "count": 23
    },
    {
      "concept": "Authoritarianism",
      "count": 23
    },
    {
      "concept": "Art",
      "count": 23
    },
    {
      "concept": "Radical right",
      "count": 22
    },
    {
      "concept": "Law and economics",
      "count": 21
    },
    {
      "concept": "Engineering",
      "count": 21
    },
    {
      "concept": "State (computer science)",
      "count": 21
    },
    {
      "concept": "Algorithm",
      "count": 21
    },
    {
      "concept": "Biology",
      "count": 21
    },
    {
      "concept": "Immigration",
      "count": 21
    },
    {
      "concept": "Geography",
      "count": 21
    },
    {
      "concept": "European union",
      "count": 20
    },
    {
      "concept": "Aesthetics",
      "count": 20
    },
    {
      "concept": "Elite",
      "count": 19
    },
    {
      "concept": "Quantum mechanics",
      "count": 18
    },
    {
      "concept": "Business",
      "count": 18
    },
    {
      "concept": "Nationalism",
      "count": 17
    },
    {
      "concept": "Public relations",
      "count": 16
    },
    {
      "concept": "Latin Americans",
      "count": 16
    },
    {
      "concept": "Opposition (politics)",
      "count": 16
    },
    {
      "concept": "Gender studies",
      "count": 15
    },
    {
      "concept": "Finance",
      "count": 15
    },
    {
      "concept": "Power (physics)",
      "count": 14
    },
    {
      "concept": "Argument (complex analysis)",
      "count": 14
    }
  ],
  "cooccurrence_matrix_top20": {
    "Political science": {
      "Political science": 0,
      "Law": 279,
      "Politics": 269,
      "Sociology": 224,
      "Political economy": 188,
      "Populism": 187,
      "Economics": 119,
      "Philosophy": 102,
      "Democracy": 82,
      "Computer science": 74,
      "Epistemology": 56,
      "Psychology": 52,
      "Ideology": 47,
      "History": 40,
      "Social psychology": 35,
      "Linguistics": 37,
      "Media studies": 35,
      "Archaeology": 29,
      "Development economics": 32,
      "Social science": 29
    },
    "Law": {
      "Political science": 279,
      "Law": 0,
      "Politics": 269,
      "Sociology": 220,
      "Political economy": 187,
      "Populism": 187,
      "Economics": 114,
      "Philosophy": 98,
      "Democracy": 82,
      "Computer science": 73,
      "Epistemology": 55,
      "Psychology": 49,
      "Ideology": 47,
      "History": 36,
      "Social psychology": 32,
      "Linguistics": 36,
      "Media studies": 35,
      "Archaeology": 28,
      "Development economics": 31,
      "Social science": 29
    },
    "Politics": {
      "Political science": 269,
      "Law": 269,
      "Politics": 0,
      "Sociology": 215,
      "Political economy": 186,
      "Populism": 187,
      "Economics": 111,
      "Philosophy": 94,
      "Democracy": 82,
      "Computer science": 72,
      "Epistemology": 55,
      "Psychology": 46,
      "Ideology": 47,
      "History": 34,
      "Social psychology": 30,
      "Linguistics": 34,
      "Media studies": 34,
      "Archaeology": 27,
      "Development economics": 31,
      "Social science": 27
    },
    "Sociology": {
      "Political science": 224,
      "Law": 220,
      "Politics": 215,
      "Sociology": 0,
      "Political economy": 155,
      "Populism": 156,
      "Economics": 81,
      "Philosophy": 94,
      "Democracy": 69,
      "Computer science": 61,
      "Epistemology": 51,
      "Psychology": 39,
      "Ideology": 46,
      "History": 28,
      "Social psychology": 26,
      "Linguistics": 35,
      "Media studies": 36,
      "Archaeology": 24,
      "Development economics": 17,
      "Social science": 30
    },
    "Political economy": {
      "Political science": 188,
      "Law": 187,
      "Politics": 186,
      "Sociology": 155,
      "Political economy": 0,
      "Populism": 138,
      "Economics": 95,
      "Philosophy": 60,
      "Democracy": 70,
      "Computer science": 44,
      "Epistemology": 31,
      "Psychology": 26,
      "Ideology": 37,
      "History": 19,
      "Social psychology": 17,
      "Linguistics": 28,
      "Media studies": 14,
      "Archaeology": 17,
      "Development economics": 28,
      "Social science": 14
    },
    "Populism": {
      "Political science": 187,
      "Law": 187,
      "Politics": 187,
      "Sociology": 156,
      "Political economy": 138,
      "Populism": 0,
      "Economics": 73,
      "Philosophy": 71,
      "Democracy": 58,
      "Computer science": 54,
      "Epistemology": 47,
      "Psychology": 39,
      "Ideology": 42,
      "History": 22,
      "Social psychology": 23,
      "Linguistics": 25,
      "Media studies": 28,
      "Archaeology": 20,
      "Development economics": 19,
      "Social science": 20
    },
    "Economics": {
      "Political science": 119,
      "Law": 114,
      "Politics": 111,
      "Sociology": 81,
      "Political economy": 95,
      "Populism": 73,
      "Economics": 0,
      "Philosophy": 41,
      "Democracy": 33,
      "Computer science": 31,
      "Epistemology": 24,
      "Psychology": 23,
      "Ideology": 17,
      "History": 11,
      "Social psychology": 15,
      "Linguistics": 14,
      "Media studies": 3,
      "Archaeology": 11,
      "Development economics": 32,
      "Social science": 10
    },
    "Philosophy": {
      "Political science": 102,
      "Law": 98,
      "Politics": 94,
      "Sociology": 94,
      "Political economy": 60,
      "Populism": 71,
      "Economics": 41,
      "Philosophy": 0,
      "Democracy": 26,
      "Computer science": 35,
      "Epistemology": 58,
      "Psychology": 19,
      "Ideology": 24,
      "History": 18,
      "Social psychology": 14,
      "Linguistics": 37,
      "Media studies": 11,
      "Archaeology": 12,
      "Development economics": 3,
      "Social science": 19
    },
    "Democracy": {
      "Political science": 82,
      "Law": 82,
      "Politics": 82,
      "Sociology": 69,
      "Political economy": 70,
      "Populism": 58,
      "Economics": 33,
      "Philosophy": 26,
      "Democracy": 0,
      "Computer science": 14,
      "Epistemology": 16,
      "Psychology": 9,
      "Ideology": 18,
      "History": 8,
      "Social psychology": 6,
      "Linguistics": 10,
      "Media studies": 9,
      "Archaeology": 5,
      "Development economics": 12,
      "Social science": 4
    },
    "Computer science": {
      "Political science": 74,
      "Law": 73,
      "Politics": 72,
      "Sociology": 61,
      "Political economy": 44,
      "Populism": 54,
      "Economics": 31,
      "Philosophy": 35,
      "Democracy": 14,
      "Computer science": 0,
      "Epistemology": 21,
      "Psychology": 17,
      "Ideology": 9,
      "History": 5,
      "Social psychology": 10,
      "Linguistics": 12,
      "Media studies": 13,
      "Archaeology": 3,
      "Development economics": 10,
      "Social science": 7
    },
    "Epistemology": {
      "Political science": 56,
      "Law": 55,
      "Politics": 55,
      "Sociology": 51,
      "Political economy": 31,
      "Populism": 47,
      "Economics": 24,
      "Philosophy": 58,
      "Democracy": 16,
      "Computer science": 21,
      "Epistemology": 0,
      "Psychology": 7,
      "Ideology": 17,
      "History": 6,
      "Social psychology": 5,
      "Linguistics": 8,
      "Media studies": 3,
      "Archaeology": 7,
      "Development economics": 1,
      "Social science": 13
    },
    "Psychology": {
      "Political science": 52,
      "Law": 49,
      "Politics": 46,
      "Sociology": 39,
      "Political economy": 26,
      "Populism": 39,
      "Economics": 23,
      "Philosophy": 19,
      "Democracy": 9,
      "Computer science": 17,
      "Epistemology": 7,
      "Psychology": 0,
      "Ideology": 7,
      "History": 8,
      "Social psychology": 37,
      "Linguistics": 7,
      "Media studies": 10,
      "Archaeology": 8,
      "Development economics": 5,
      "Social science": 9
    },
    "Ideology": {
      "Political science": 47,
      "Law": 47,
      "Politics": 47,
      "Sociology": 46,
      "Political economy": 37,
      "Populism": 42,
      "Economics": 17,
      "Philosophy": 24,
      "Democracy": 18,
      "Computer science": 9,
      "Epistemology": 17,
      "Psychology": 7,
      "Ideology": 0,
      "History": 5,
      "Social psychology": 6,
      "Linguistics": 8,
      "Media studies": 2,
      "Archaeology": 5,
      "Development economics": 1,
      "Social science": 6
    },
    "History": {
      "Political science": 40,
      "Law": 36,
      "Politics": 34,
      "Sociology": 28,
      "Political economy": 19,
      "Populism": 22,
      "Economics": 11,
      "Philosophy": 18,
      "Democracy": 8,
      "Computer science": 5,
      "Epistemology": 6,
      "Psychology": 8,
      "Ideology": 5,
      "History": 0,
      "Social psychology": 5,
      "Linguistics": 5,
      "Media studies": 7,
      "Archaeology": 21,
      "Development economics": 5,
      "Social science": 4
    },
    "Social psychology": {
      "Political science": 35,
      "Law": 32,
      "Politics": 30,
      "Sociology": 26,
      "Political economy": 17,
      "Populism": 23,
      "Economics": 15,
      "Philosophy": 14,
      "Democracy": 6,
      "Computer science": 10,
      "Epistemology": 5,
      "Psychology": 37,
      "Ideology": 6,
      "History": 5,
      "Social psychology": 0,
      "Linguistics": 6,
      "Media studies": 4,
      "Archaeology": 6,
      "Development economics": 3,
      "Social science": 7
    },
    "Linguistics": {
      "Political science": 37,
      "Law": 36,
      "Politics": 34,
      "Sociology": 35,
      "Political economy": 28,
      "Populism": 25,
      "Economics": 14,
      "Philosophy": 37,
      "Democracy": 10,
      "Computer science": 12,
      "Epistemology": 8,
      "Psychology": 7,
      "Ideology": 8,
      "History": 5,
      "Social psychology": 6,
      "Linguistics": 0,
      "Media studies": 6,
      "Archaeology": 2,
      "Development economics": 2,
      "Social science": 4
    },
    "Media studies": {
      "Political science": 35,
      "Law": 35,
      "Politics": 34,
      "Sociology": 36,
      "Political economy": 14,
      "Populism": 28,
      "Economics": 3,
      "Philosophy": 11,
      "Democracy": 9,
      "Computer science": 13,
      "Epistemology": 3,
      "Psychology": 10,
      "Ideology": 2,
      "History": 7,
      "Social psychology": 4,
      "Linguistics": 6,
      "Media studies": 0,
      "Archaeology": 5,
      "Development economics": 0,
      "Social science": 6
    },
    "Archaeology": {
      "Political science": 29,
      "Law": 28,
      "Politics": 27,
      "Sociology": 24,
      "Political economy": 17,
      "Populism": 20,
      "Economics": 11,
      "Philosophy": 12,
      "Democracy": 5,
      "Computer science": 3,
      "Epistemology": 7,
      "Psychology": 8,
      "Ideology": 5,
      "History": 21,
      "Social psychology": 6,
      "Linguistics": 2,
      "Media studies": 5,
      "Archaeology": 0,
      "Development economics": 5,
      "Social science": 6
    },
    "Development economics": {
      "Political science": 32,
      "Law": 31,
      "Politics": 31,
      "Sociology": 17,
      "Political economy": 28,
      "Populism": 19,
      "Economics": 32,
      "Philosophy": 3,
      "Democracy": 12,
      "Computer science": 10,
      "Epistemology": 1,
      "Psychology": 5,
      "Ideology": 1,
      "History": 5,
      "Social psychology": 3,
      "Linguistics": 2,
      "Media studies": 0,
      "Archaeology": 5,
      "Development economics": 0,
      "Social science": 0
    },
    "Social science": {
      "Political science": 29,
      "Law": 29,
      "Politics": 27,
      "Sociology": 30,
      "Political economy": 14,
      "Populism": 20,
      "Economics": 10,
      "Philosophy": 19,
      "Democracy": 4,
      "Computer science": 7,
      "Epistemology": 13,
      "Psychology": 9,
      "Ideology": 6,
      "History": 4,
      "Social psychology": 7,
      "Linguistics": 4,
      "Media studies": 6,
      "Archaeology": 6,
      "Development economics": 0,
      "Social science": 0
    }
  }
}